freactor/__init__.py
freactor/lib.py
freactor/lib_async.py
freactor-1.0.1.dist-info/licenses/LICENSE
freactor-1.0.1.dist-info/METADATA
freactor-1.0.1.dist-info/WHEEL
freactor-1.0.1.dist-info/top_level.txt
freactor-1.0.1.dist-info/RECORD
